pysimulation.py
pysimulation-1.9.dist-info/LICENSE
pysimulation-1.9.dist-info/METADATA
pysimulation-1.9.dist-info/WHEEL
pysimulation-1.9.dist-info/top_level.txt
pysimulation-1.9.dist-info/RECORD
