Metadata-Version: 2.1
Name: pysimulation
Version: 1.9
Author: rakson
License: MIT
License-File: LICENSE
Requires-Dist: pandas
Requires-Dist: pytz
